testingpkg/__init__.py
testingpkg-0.0.1.dist-info/METADATA
testingpkg-0.0.1.dist-info/WHEEL
testingpkg-0.0.1.dist-info/top_level.txt
testingpkg-0.0.1.dist-info/RECORD
