Metadata-Version: 2.1
Name: testingpkg
Version: 0.0.1
Summary: A simple test package.
License: MIT
Keywords: python,test,pip
Classifier: Programming Language :: Python :: 3
